mkdocs_overwrite_configs/__init__.py
mkdocs_overwrite_configs/plugin.py
mkdocs_overwrite_configs-1.0.1.dist-info/METADATA
mkdocs_overwrite_configs-1.0.1.dist-info/WHEEL
mkdocs_overwrite_configs-1.0.1.dist-info/entry_points.txt
mkdocs_overwrite_configs-1.0.1.dist-info/top_level.txt
mkdocs_overwrite_configs-1.0.1.dist-info/RECORD
