Metadata-Version: 2.1
Name: mkdocs-overwrite-configs
Version: 1.0.1
Summary: Overwrite MkDocs configuration files with a single file
Author-email: carneirofc <claudiofcarneiro@hotmail.com>
License: MIT
Project-URL: homepage, https://github.com/carneirofc/mkdocs-overwrite-configs
Keywords: mkdocs,backstage,techdocs,mkdocs-overwrite-configs
Classifier: Development Status :: 4 - Beta
Classifier: Intended Audience :: Developers
Classifier: Intended Audience :: Information Technology
Classifier: License :: OSI Approved :: MIT License
Classifier: Programming Language :: Python
Classifier: Programming Language :: Python :: 3 :: Only
Classifier: Programming Language :: Python :: 3.12
Requires-Python: >=3.6
Requires-Dist: mkdocs>=1.1
